[
    {
        "id": 6,
        "title": "Smart Agency LP",
        "link": "projects/pet-projects/6-MineLP",
        "locale": true,
        "stack": "html, css, bootstrap4",
        "source": "https://github.com/Kushbak/Portfolio-website/public/projects/pet-projects/6-MineLP"
    },
    {
        "id": 5,
        "title": "Simple LP",
        "link": "projects/pet-projects/5-AgencyLP",
        "locale": true,
        "stack": "html, css, bootstrap4",
        "source": "https://github.com/Kushbak/Portfolio-website/public/projects/pet-projects/5-AgencyLP"
    },
    {
        "id": 4,
        "title": "Landing made with MDB",
        "link": "projects/pet-projects/4-MDBProject",
        "locale": true,
        "stack": "html, css, bootstrap4",
        "source": "https://github.com/Kushbak/Portfolio-website/public/projects/pet-projects/4-MDBProject"
    },
    {
        "id": 3,
        "title": "Corporate",
        "link": "projects/pet-projects/3-Corporate",
        "locale": true,
        "stack": "html, css, less, bootstrap4",
        "source": "https://github.com/Kushbak/Portfolio-website/public/projects/pet-projects/3-Corporate"
    },
    {
        "id": 2,
        "title": "Landing with Bootstrap",
        "link": "projects/pet-projects/2-MDB",
        "locale": true,
        "description": {
            "ru": "Первый опыт с Bootstrap и MDB",
            "en": "First work with Bootstrap and MDB"
        },
        "stack": "html, css, less, bootstrap4",
        "source": "https://github.com/Kushbak/Portfolio-website/public/projects/pet-projects/2-MDB"
    },
    {
        "id": 1,
        "title": "My 1st simple web-site",
        "link": "projects/pet-projects/1-Mycompany",
        "locale": true,
        "description": {
            "ru": "Первый сайт, оставлю его тут на память",
            "en": "The first site, I'll leave it here as a memento"
        },
        "stack": "html, css, less",
        "source": "https://github.com/Kushbak/Portfolio-website/public/projects/pet-projects/1-Mycompany"
    }
]